README.md
setup.py
bnmp_scraper/__init__.py
bnmp_scraper/api.py
bnmp_scraper/errors.py
bnmp_scraper/extrator.py
bnmp_scraper/filtro.py
bnmp_scraper/settings.py
bnmp_scraper/utils.py
bnmp_scraper.egg-info/PKG-INFO
bnmp_scraper.egg-info/SOURCES.txt
bnmp_scraper.egg-info/dependency_links.txt
bnmp_scraper.egg-info/requires.txt
bnmp_scraper.egg-info/top_level.txt