Metadata-Version: 2.1
Name: bnmp-scraper
Version: 1.0.0
Summary: Navega pela API do Portal BNMP coletando dados
Home-page: https://github.com/olucaslopes/BNMP-Scraper
Author: Lucas Lopes
Author-email: lucaslopesamorim@gmail.com
License: UNKNOWN
Platform: UNKNOWN
